odoo8_addon_hr_contract_reference-8.0.1.0.0.99.dev7-py2.7-nspkg.pth
odoo8_addon_hr_contract_reference-8.0.1.0.0.99.dev7.dist-info/DESCRIPTION.rst
odoo8_addon_hr_contract_reference-8.0.1.0.0.99.dev7.dist-info/METADATA
odoo8_addon_hr_contract_reference-8.0.1.0.0.99.dev7.dist-info/RECORD
odoo8_addon_hr_contract_reference-8.0.1.0.0.99.dev7.dist-info/WHEEL
odoo8_addon_hr_contract_reference-8.0.1.0.0.99.dev7.dist-info/metadata.json
odoo8_addon_hr_contract_reference-8.0.1.0.0.99.dev7.dist-info/namespace_packages.txt
odoo8_addon_hr_contract_reference-8.0.1.0.0.99.dev7.dist-info/top_level.txt
odoo_addons/hr_contract_reference/README.rst
odoo_addons/hr_contract_reference/__init__.py
odoo_addons/hr_contract_reference/__openerp__.py
odoo_addons/hr_contract_reference/data/hr_contract_sequence.xml
odoo_addons/hr_contract_reference/i18n/ca.po
odoo_addons/hr_contract_reference/i18n/de.po
odoo_addons/hr_contract_reference/i18n/es.po
odoo_addons/hr_contract_reference/i18n/fi.po
odoo_addons/hr_contract_reference/i18n/fr.po
odoo_addons/hr_contract_reference/i18n/hr_contract_reference.pot
odoo_addons/hr_contract_reference/i18n/it.po
odoo_addons/hr_contract_reference/i18n/pt_BR.po
odoo_addons/hr_contract_reference/i18n/ro.po
odoo_addons/hr_contract_reference/i18n/sl.po
odoo_addons/hr_contract_reference/i18n/zh_CN.po
odoo_addons/hr_contract_reference/models/__init__.py
odoo_addons/hr_contract_reference/models/hr_contract.py
odoo_addons/hr_contract_reference/static/description/icon.png
odoo_addons/hr_contract_reference/views/hr_contract_view.xml
